iqtoolkit_analyzer/__init__.py
iqtoolkit_analyzer/__main__.py
iqtoolkit_analyzer/__version__.py
iqtoolkit_analyzer/analyzer.py
iqtoolkit_analyzer/antipatterns.py
iqtoolkit_analyzer/api/main.py
iqtoolkit_analyzer/config.py
iqtoolkit_analyzer/explain_antipatterns.py
iqtoolkit_analyzer/explain_metrics.py
iqtoolkit_analyzer/explain_parser.py
iqtoolkit_analyzer/explain_recommender.py
iqtoolkit_analyzer/llm_client.py
iqtoolkit_analyzer/main.py
iqtoolkit_analyzer/mongodb_analyzer.py
iqtoolkit_analyzer/mongodb_cli.py
iqtoolkit_analyzer/mongodb_config.py
iqtoolkit_analyzer/mongodb_report_generator.py
iqtoolkit_analyzer/parser.py
iqtoolkit_analyzer/report_generator.py
iqtoolkit_analyzer/test.txt
iqtoolkit_analyzer-0.2.8.dist-info/METADATA
iqtoolkit_analyzer-0.2.8.dist-info/WHEEL
iqtoolkit_analyzer-0.2.8.dist-info/entry_points.txt
iqtoolkit_analyzer-0.2.8.dist-info/licenses/LICENSE
iqtoolkit_analyzer-0.2.8.dist-info/RECORD
