Metadata-Version: 2.4
Name: iqtoolkit-analyzer
Version: 0.2.8
Summary: AI-powered multi-database performance analyzer for PostgreSQL and MongoDB with privacy-first intelligence
License-Expression: MIT
License-File: LICENSE
Keywords: postgresql,mongodb,database,performance,optimization,sql,ai,openai,slow-queries,analyzer
Author: Giovanni Martinez
Author-email: gio@iqtoolkit.ai
Maintainer: Giovanni Martinez
Maintainer-email: gio@iqtoolkit.ai
Requires-Python: >=3.11,<4.0
Classifier: Development Status :: 4 - Beta
Classifier: Intended Audience :: Developers
Classifier: Intended Audience :: System Administrators
Classifier: Operating System :: OS Independent
Classifier: Programming Language :: Python :: 3
Classifier: Programming Language :: Python :: 3.11
Classifier: Programming Language :: Python :: 3.12
Classifier: Programming Language :: SQL
Classifier: Topic :: Database
Classifier: Topic :: Software Development :: Libraries :: Python Modules
Classifier: Topic :: System :: Systems Administration
Classifier: Topic :: Scientific/Engineering :: Artificial Intelligence
Provides-Extra: all
Provides-Extra: cloud-ai
Provides-Extra: docs
Requires-Dist: anthropic (>=0.18.0) ; extra == "all"
Requires-Dist: anthropic (>=0.18.0) ; extra == "cloud-ai"
Requires-Dist: boto3 (>=1.42.16) ; extra == "all"
Requires-Dist: boto3 (>=1.42.16) ; extra == "cloud-ai"
Requires-Dist: colorama (>=0.4.6)
Requires-Dist: fastapi (>=0.100.0)
Requires-Dist: google-generativeai (>=0.3.0) ; extra == "all"
Requires-Dist: google-generativeai (>=0.3.0) ; extra == "cloud-ai"
Requires-Dist: mkdocs (>=1.4.0) ; extra == "docs"
Requires-Dist: mkdocs-material (>=9.0.0) ; extra == "docs"
Requires-Dist: mkdocs-mermaid2-plugin (>=1.0.0) ; extra == "docs"
Requires-Dist: ollama
Requires-Dist: openai (>=1.0.0)
Requires-Dist: pandas (>=2.0.0)
Requires-Dist: platformdirs (>=3.0.0)
Requires-Dist: psycopg[binary] (>=3.1.18)
Requires-Dist: pymongo (>=4.6.0) ; extra == "all"
Requires-Dist: python-dotenv (>=0.19.0)
Requires-Dist: pyyaml (>=6.0.0)
Requires-Dist: ruamel.yaml (>=0.17.21)
Requires-Dist: tqdm (>=4.0.0)
Requires-Dist: uvicorn (>=0.23.2)
Project-URL: Homepage, https://github.com/iqtoolkit/iqtoolkit-analyzer
Project-URL: Repository, https://github.com/iqtoolkit/iqtoolkit-analyzer
